Workbook

Sheet 月度成本明细
A1: 月份 | B1: 部门 | C1: 成本类别 | D1: 金额(万元) | E1: 预算(万元) | F1: 是否超支
A2: 2025-01 | B2: 研发部 | C2: 人力成本 | D2: 18.44 | E2: 15.97 | F2: 是
A3: 2025-01 | B3: 研发部 | C3: 云服务器费用 | D3: 46.72 | E3: 58.02 | F3: 否
A4: 2025-01 | B4: 研发部 | C4: 市场推广费 | D4: 27.5 | E4: 22.66 | F4: 是
A5: 2025-01 | B5: 研发部 | C5: 办公租金 | D5: 50.17 | E5: 40.52 | F5: 是
A6: 2025-01 | B6: 研发部 | C6: 设备采购 | D6: 65.72 | E6: 54.94 | F6: 是
A7: 2025-01 | B7: 研发部 | C7: 培训费用 | D7: 10.01 | E7: 9.92 | F7: 是
A8: 2025-01 | B8: 研发部 | C8: 差旅费 | D8: 27.51 | E8: 36.58 | F8: 否
A9: 2025-01 | B9: 市场部 | C9: 人力成本 | D9: 37.93 | E9: 34.43 | F9: 是
A10: 2025-01 | B10: 市场部 | C10: 云服务器费用 | D10: 36.3 | E10: 44.77 | F10: 否
A11: 2025-01 | B11: 市场部 | C11: 市场推广费 | D11: 44.33 | E11: 56.52 | F11: 否
A12: 2025-01 | B12: 市场部 | C12: 办公租金 | D12: 49.38 | E12: 55.23 | F12: 否
A13: 2025-01 | B13: 市场部 | C13: 设备采购 | D13: 12.42 | E13: 14.63 | F13: 否
... A505: 2025-12 | B505: 行政部 | C505: 差旅费 | D505: 27.86 | E505: 36.23 | F505: 否

Sheet 供应商采购成本
A1: 供应商名称 | B1: 采购类别 | C1: 采购日期 | D1: 采购金额(万元) | E1: 付款状态
A2: 鑫盛办公用品 | B2: 设备采购 | C2: 45933 | D2: 20.49 | E2: 待付款
A3: 蓝海云计算 | B3: 云服务器费用 | C3: 45781 | D3: 6.31 | E3: 部分付款
A4: 极速网络科技 | B4: 设备采购 | C4: 45852 | D4: 18.3 | E4: 部分付款
A5: 华科设备供应 | B5: 办公租金 | C5: 45732 | D5: 19.43 | E5: 部分付款
A6: 创新市场传媒 | B6: 云服务器费用 | C6: 45906 | D6: 15.2 | E6: 已付款
A7: 极速网络科技 | B7: 市场推广费 | C7: 45889 | D7: 2.55 | E7: 待付款
A8: 蓝海云计算 | B8: 办公租金 | C8: 45723 | D8: 24.64 | E8: 部分付款
A9: 优选人力资源 | B9: 培训费用 | C9: 45883 | D9: 20.86 | E9: 待付款
A10: 创新市场传媒 | B10: 差旅费 | C10: 45885 | D10: 5.85 | E10: 部分付款
A11: 蓝海云计算 | B11: 差旅费 | C11: 45757 | D11: 1.95 | E11: 已付款
A12: 优选人力资源 | B12: 市场推广费 | C12: 45741 | D12: 14.26 | E12: 部分付款
A13: 华科设备供应 | B13: 设备采购 | C13: 45904 | D13: 17.61 | E13: 待付款
... A151: 创新市场传媒 | B151: 设备采购 | C151: 45799 | D151: 9.16 | E151: 已付款

Sheet 分类整理
A2: 月份 | C2: 成本类别 | E2: 部门
A3: {=IFERROR(INDEX(月度成本明细!$A$2:$A$5000,MATCH(0,COUNTIF($A$1:A2,月度成本明细!$A$2:$A$5000)+IF(月度成本明细!$A$2:$A$5000="",1,0),0)),"")} -> 2025-01 | C3: {=IFERROR(INDEX(供应商采购成本!$B$2:$B$5000,MATCH(0,COUNTIF($A$1:C2,供应商采购成本!$B$2:$B$5000)+IF(供应商采购成本!$B$2:$B$5000="",1,0),0)),"")} -> 设备采购 | E3: {=IFERROR(INDEX(月度成本明细!$B$2:$B$5000,MATCH(0,COUNTIF($A$1:E2,月度成本明细!$B$2:$B$5000)+IF(月度成本明细!$B$2:$B$5000="",1,0),0)),"")} -> 研发部
A4: {=IFERROR(INDEX(月度成本明细!$A$2:$A$5000,MATCH(0,COUNTIF($A$1:A3,月度成本明细!$A$2:$A$5000)+IF(月度成本明细!$A$2:$A$5000="",1,0),0)),"")} -> 2025-02 | C4: {=IFERROR(INDEX(供应商采购成本!$B$2:$B$5000,MATCH(0,COUNTIF($A$1:C3,供应商采购成本!$B$2:$B$5000)+IF(供应商采购成本!$B$2:$B$5000="",1,0),0)),"")} -> 云服务器费用 | E4: {=IFERROR(INDEX(月度成本明细!$B$2:$B$5000,MATCH(0,COUNTIF($A$1:E3,月度成本明细!$B$2:$B$5000)+IF(月度成本明细!$B$2:$B$5000="",1,0),0)),"")} -> 市场部
A5: {=IFERROR(INDEX(月度成本明细!$A$2:$A$5000,MATCH(0,COUNTIF($A$1:A4,月度成本明细!$A$2:$A$5000)+IF(月度成本明细!$A$2:$A$5000="",1,0),0)),"")} -> 2025-03 | C5: {=IFERROR(INDEX(供应商采购成本!$B$2:$B$5000,MATCH(0,COUNTIF($A$1:C4,供应商采购成本!$B$2:$B$5000)+IF(供应商采购成本!$B$2:$B$5000="",1,0),0)),"")} -> 办公租金 | E5: {=IFERROR(INDEX(月度成本明细!$B$2:$B$5000,MATCH(0,COUNTIF($A$1:E4,月度成本明细!$B$2:$B$5000)+IF(月度成本明细!$B$2:$B$5000="",1,0),0)),"")} -> 销售部
A6: {=IFERROR(INDEX(月度成本明细!$A$2:$A$5000,MATCH(0,COUNTIF($A$1:A5,月度成本明细!$A$2:$A$5000)+IF(月度成本明细!$A$2:$A$5000="",1,0),0)),"")} -> 2025-04 | C6: {=IFERROR(INDEX(供应商采购成本!$B$2:$B$5000,MATCH(0,COUNTIF($A$1:C5,供应商采购成本!$B$2:$B$5000)+IF(供应商采购成本!$B$2:$B$5000="",1,0),0)),"")} -> 市场推广费 | E6: {=IFERROR(INDEX(月度成本明细!$B$2:$B$5000,MATCH(0,COUNTIF($A$1:E5,月度成本明细!$B$2:$B$5000)+IF(月度成本明细!$B$2:$B$5000="",1,0),0)),"")} -> 运营部
A7: {=IFERROR(INDEX(月度成本明细!$A$2:$A$5000,MATCH(0,COUNTIF($A$1:A6,月度成本明细!$A$2:$A$5000)+IF(月度成本明细!$A$2:$A$5000="",1,0),0)),"")} -> 2025-05 | C7: {=IFERROR(INDEX(供应商采购成本!$B$2:$B$5000,MATCH(0,COUNTIF($A$1:C6,供应商采购成本!$B$2:$B$5000)+IF(供应商采购成本!$B$2:$B$5000="",1,0),0)),"")} -> 培训费用 | E7: {=IFERROR(INDEX(月度成本明细!$B$2:$B$5000,MATCH(0,COUNTIF($A$1:E6,月度成本明细!$B$2:$B$5000)+IF(月度成本明细!$B$2:$B$5000="",1,0),0)),"")} -> 人力资源部
A8: {=IFERROR(INDEX(月度成本明细!$A$2:$A$5000,MATCH(0,COUNTIF($A$1:A7,月度成本明细!$A$2:$A$5000)+IF(月度成本明细!$A$2:$A$5000="",1,0),0)),"")} -> 2025-06 | C8: {=IFERROR(INDEX(供应商采购成本!$B$2:$B$5000,MATCH(0,COUNTIF($A$1:C7,供应商采购成本!$B$2:$B$5000)+IF(供应商采购成本!$B$2:$B$5000="",1,0),0)),"")} -> 差旅费 | E8: {=IFERROR(INDEX(月度成本明细!$B$2:$B$5000,MATCH(0,COUNTIF($A$1:E7,月度成本明细!$B$2:$B$5000)+IF(月度成本明细!$B$2:$B$5000="",1,0),0)),"")} -> 行政部
A9: {=IFERROR(INDEX(月度成本明细!$A$2:$A$5000,MATCH(0,COUNTIF($A$1:A8,月度成本明细!$A$2:$A$5000)+IF(月度成本明细!$A$2:$A$5000="",1,0),0)),"")} -> 2025-07 | C9: {=IFERROR(INDEX(供应商采购成本!$B$2:$B$5000,MATCH(0,COUNTIF($A$1:C8,供应商采购成本!$B$2:$B$5000)+IF(供应商采购成本!$B$2:$B$5000="",1,0),0)),"")} -> 人力成本 | E9: {=IFERROR(INDEX(月度成本明细!$B$2:$B$5000,MATCH(0,COUNTIF($A$1:E8,月度成本明细!$B$2:$B$5000)+IF(月度成本明细!$B$2:$B$5000="",1,0),0)),"")}
A10: {=IFERROR(INDEX(月度成本明细!$A$2:$A$5000,MATCH(0,COUNTIF($A$1:A9,月度成本明细!$A$2:$A$5000)+IF(月度成本明细!$A$2:$A$5000="",1,0),0)),"")} -> 2025-08 | C10: {=IFERROR(INDEX(供应商采购成本!$B$2:$B$5000,MATCH(0,COUNTIF($A$1:C9,供应商采购成本!$B$2:$B$5000)+IF(供应商采购成本!$B$2:$B$5000="",1,0),0)),"")} | E10: {=IFERROR(INDEX(月度成本明细!$B$2:$B$5000,MATCH(0,COUNTIF($A$1:E9,月度成本明细!$B$2:$B$5000)+IF(月度成本明细!$B$2:$B$5000="",1,0),0)),"")}
A11: {=IFERROR(INDEX(月度成本明细!$A$2:$A$5000,MATCH(0,COUNTIF($A$1:A10,月度成本明细!$A$2:$A$5000)+IF(月度成本明细!$A$2:$A$5000="",1,0),0)),"")} -> 2025-09 | C11: {=IFERROR(INDEX(供应商采购成本!$B$2:$B$5000,MATCH(0,COUNTIF($A$1:C10,供应商采购成本!$B$2:$B$5000)+IF(供应商采购成本!$B$2:$B$5000="",1,0),0)),"")} | E11: {=IFERROR(INDEX(月度成本明细!$B$2:$B$5000,MATCH(0,COUNTIF($A$1:E10,月度成本明细!$B$2:$B$5000)+IF(月度成本明细!$B$2:$B$5000="",1,0),0)),"")}
A12: {=IFERROR(INDEX(月度成本明细!$A$2:$A$5000,MATCH(0,COUNTIF($A$1:A11,月度成本明细!$A$2:$A$5000)+IF(月度成本明细!$A$2:$A$5000="",1,0),0)),"")} -> 2025-10 | C12: {=IFERROR(INDEX(供应商采购成本!$B$2:$B$5000,MATCH(0,COUNTIF($A$1:C11,供应商采购成本!$B$2:$B$5000)+IF(供应商采购成本!$B$2:$B$5000="",1,0),0)),"")} | E12: {=IFERROR(INDEX(月度成本明细!$B$2:$B$5000,MATCH(0,COUNTIF($A$1:E11,月度成本明细!$B$2:$B$5000)+IF(月度成本明细!$B$2:$B$5000="",1,0),0)),"")}
A13: {=IFERROR(INDEX(月度成本明细!$A$2:$A$5000,MATCH(0,COUNTIF($A$1:A12,月度成本明细!$A$2:$A$5000)+IF(月度成本明细!$A$2:$A$5000="",1,0),0)),"")} -> 2025-11 | C13: {=IFERROR(INDEX(供应商采购成本!$B$2:$B$5000,MATCH(0,COUNTIF($A$1:C12,供应商采购成本!$B$2:$B$5000)+IF(供应商采购成本!$B$2:$B$5000="",1,0),0)),"")} | E13: {=IFERROR(INDEX(月度成本明细!$B$2:$B$5000,MATCH(0,COUNTIF($A$1:E12,月度成本明细!$B$2:$B$5000)+IF(月度成本明细!$B$2:$B$5000="",1,0),0)),"")}
A14: {=IFERROR(INDEX(月度成本明细!$A$2:$A$5000,MATCH(0,COUNTIF($A$1:A13,月度成本明细!$A$2:$A$5000)+IF(月度成本明细!$A$2:$A$5000="",1,0),0)),"")} -> 2025-12 | C14: {=IFERROR(INDEX(供应商采购成本!$B$2:$B$5000,MATCH(0,COUNTIF($A$1:C13,供应商采购成本!$B$2:$B$5000)+IF(供应商采购成本!$B$2:$B$5000="",1,0),0)),"")} | E14: {=IFERROR(INDEX(月度成本明细!$B$2:$B$5000,MATCH(0,COUNTIF($A$1:E13,月度成本明细!$B$2:$B$5000)+IF(月度成本明细!$B$2:$B$5000="",1,0),0)),"")}

Sheet 成本分析看板
A1: 成本分析看板（月份/成本类别取自「数据整理」的去重结果，数值为公式联动）
A3: 一、月度成本趋势（数据来源：月度成本明细，经「数据整理」去重分组）
A4: 月份 | B4: 总支出(万元) | C4: 总预算(万元) | D4: 差异(万元) | E4: 预算执行率 | F4: 超支占比 | G4: 超支笔数 | H4: 总笔数
A5: =分类整理!A3 -> 2025-01 | B5: =IF($A5="","",SUMIF(月度成本明细!$A:$A,$A5,月度成本明细!$D:$D)) -> 1526.36 | C5: =IF($A5="","",SUMIF(月度成本明细!$A:$A,$A5,月度成本明细!$E:$E)) -> 1544.04 | D5: =IF($A5="","",B5-C5) -> -17.68 | E5: =IF($A5="","",B5/C5) -> 0.98854952 | F5: =IF($A5="","",G5/H5) -> 0.47619048 | G5: =IF($A5="","",COUNTIFS(月度成本明细!$A:$A,$A5,月度成本明细!$F:$F,"是")) -> 20 | H5: =IF($A5="","",COUNTIF(月度成本明细!$A:$A,$A5)) -> 42
A6: =分类整理!A4 -> 2025-02 | B6: =IF($A6="","",SUMIF(月度成本明细!$A:$A,$A6,月度成本明细!$D:$D)) -> 1485.63 | C6: =IF($A6="","",SUMIF(月度成本明细!$A:$A,$A6,月度成本明细!$E:$E)) -> 1544.04 | D6: =IF($A6="","",B6-C6) -> -58.41 | E6: =IF($A6="","",B6/C6) -> 0.96217067 | F6: =IF($A6="","",G6/H6) -> 0.5 | G6: =IF($A6="","",COUNTIFS(月度成本明细!$A:$A,$A6,月度成本明细!$F:$F,"是")) -> 21 | H6: =IF($A6="","",COUNTIF(月度成本明细!$A:$A,$A6)) -> 42
A7: =分类整理!A5 -> 2025-03 | B7: =IF($A7="","",SUMIF(月度成本明细!$A:$A,$A7,月度成本明细!$D:$D)) -> 1569.52 | C7: =IF($A7="","",SUMIF(月度成本明细!$A:$A,$A7,月度成本明细!$E:$E)) -> 1544.04 | D7: =IF($A7="","",B7-C7) -> 25.48 | E7: =IF($A7="","",B7/C7) -> 1.0165022 | F7: =IF($A7="","",G7/H7) -> 0.54761905 | G7: =IF($A7="","",COUNTIFS(月度成本明细!$A:$A,$A7,月度成本明细!$F:$F,"是")) -> 23 | H7: =IF($A7="","",COUNTIF(月度成本明细!$A:$A,$A7)) -> 42
A8: =分类整理!A6 -> 2025-04 | B8: =IF($A8="","",SUMIF(月度成本明细!$A:$A,$A8,月度成本明细!$D:$D)) -> 1581.05 | C8: =IF($A8="","",SUMIF(月度成本明细!$A:$A,$A8,月度成本明细!$E:$E)) -> 1544.04 | D8: =IF($A8="","",B8-C8) -> 37.01 | E8: =IF($A8="","",B8/C8) -> 1.0239696 | F8: =IF($A8="","",G8/H8) -> 0.5 | G8: =IF($A8="","",COUNTIFS(月度成本明细!$A:$A,$A8,月度成本明细!$F:$F,"是")) -> 21 | H8: =IF($A8="","",COUNTIF(月度成本明细!$A:$A,$A8)) -> 42
A9: =分类整理!A7 -> 2025-05 | B9: =IF($A9="","",SUMIF(月度成本明细!$A:$A,$A9,月度成本明细!$D:$D)) -> 1651.18 | C9: =IF($A9="","",SUMIF(月度成本明细!$A:$A,$A9,月度成本明细!$E:$E)) -> 1544.04 | D9: =IF($A9="","",B9-C9) -> 107.14 | E9: =IF($A9="","",B9/C9) -> 1.0693894 | F9: =IF($A9="","",G9/H9) -> 0.5952381 | G9: =IF($A9="","",COUNTIFS(月度成本明细!$A:$A,$A9,月度成本明细!$F:$F,"是")) -> 25 | H9: =IF($A9="","",COUNTIF(月度成本明细!$A:$A,$A9)) -> 42
A10: =分类整理!A8 -> 2025-06 | B10: =IF($A10="","",SUMIF(月度成本明细!$A:$A,$A10,月度成本明细!$D:$D)) -> 1572.07 | C10: =IF($A10="","",SUMIF(月度成本明细!$A:$A,$A10,月度成本明细!$E:$E)) -> 1544.04 | D10: =IF($A10="","",B10-C10) -> 28.03 | E10: =IF($A10="","",B10/C10) -> 1.0181537 | F10: =IF($A10="","",G10/H10) -> 0.52380952 | G10: =IF($A10="","",COUNTIFS(月度成本明细!$A:$A,$A10,月度成本明细!$F:$F,"是")) -> 22 | H10: =IF($A10="","",COUNTIF(月度成本明细!$A:$A,$A10)) -> 42
A11: =分类整理!A9 -> 2025-07 | B11: =IF($A11="","",SUMIF(月度成本明细!$A:$A,$A11,月度成本明细!$D:$D)) -> 1519.52 | C11: =IF($A11="","",SUMIF(月度成本明细!$A:$A,$A11,月度成本明细!$E:$E)) -> 1544.04 | D11: =IF($A11="","",B11-C11) -> -24.52 | E11: =IF($A11="","",B11/C11) -> 0.98411958 | F11: =IF($A11="","",G11/H11) -> 0.52380952 | G11: =IF($A11="","",COUNTIFS(月度成本明细!$A:$A,$A11,月度成本明细!$F:$F,"是")) -> 22 | H11: =IF($A11="","",COUNTIF(月度成本明细!$A:$A,$A11)) -> 42
A12: =分类整理!A10 -> 2025-08 | B12: =IF($A12="","",SUMIF(月度成本明细!$A:$A,$A12,月度成本明细!$D:$D)) -> 1564.69 | C12: =IF($A12="","",SUMIF(月度成本明细!$A:$A,$A12,月度成本明细!$E:$E)) -> 1544.04 | D12: =IF($A12="","",B12-C12) -> 20.65 | E12: =IF($A12="","",B12/C12) -> 1.013374 | F12: =IF($A12="","",G12/H12) -> 0.5 | G12: =IF($A12="","",COUNTIFS(月度成本明细!$A:$A,$A12,月度成本明细!$F:$F,"是")) -> 21 | H12: =IF($A12="","",COUNTIF(月度成本明细!$A:$A,$A12)) -> 42
A13: =分类整理!A11 -> 2025-09 | B13: =IF($A13="","",SUMIF(月度成本明细!$A:$A,$A13,月度成本明细!$D:$D)) -> 1493.08 | C13: =IF($A13="","",SUMIF(月度成本明细!$A:$A,$A13,月度成本明细!$E:$E)) -> 1544.04 | D13: =IF($A13="","",B13-C13) -> -50.96 | E13: =IF($A13="","",B13/C13) -> 0.96699567 | F13: =IF($A13="","",G13/H13) -> 0.4047619 | G13: =IF($A13="","",COUNTIFS(月度成本明细!$A:$A,$A13,月度成本明细!$F:$F,"是")) -> 17 | H13: =IF($A13="","",COUNTIF(月度成本明细!$A:$A,$A13)) -> 42
A14: =分类整理!A12 -> 2025-10 | B14: =IF($A14="","",SUMIF(月度成本明细!$A:$A,$A14,月度成本明细!$D:$D)) -> 1479.81 | C14: =IF($A14="","",SUMIF(月度成本明细!$A:$A,$A14,月度成本明细!$E:$E)) -> 1544.04 | D14: =IF($A14="","",B14-C14) -> -64.23 | E14: =IF($A14="","",B14/C14) -> 0.95840134 | F14: =IF($A14="","",G14/H14) -> 0.35714286 | G14: =IF($A14="","",COUNTIFS(月度成本明细!$A:$A,$A14,月度成本明细!$F:$F,"是")) -> 15 | H14: =IF($A14="","",COUNTIF(月度成本明细!$A:$A,$A14)) -> 42
A15: =分类整理!A13 -> 2025-11 | B15: =IF($A15="","",SUMIF(月度成本明细!$A:$A,$A15,月度成本明细!$D:$D)) -> 1618.53 | C15: =IF($A15="","",SUMIF(月度成本明细!$A:$A,$A15,月度成本明细!$E:$E)) -> 1544.04 | D15: =IF($A15="","",B15-C15) -> 74.49 | E15: =IF($A15="","",B15/C15) -> 1.0482436 | F15: =IF($A15="","",G15/H15) -> 0.61904762 | G15: =IF($A15="","",COUNTIFS(月度成本明细!$A:$A,$A15,月度成本明细!$F:$F,"是")) -> 26 | H15: =IF($A15="","",COUNTIF(月度成本明细!$A:$A,$A15)) -> 42
A16: =分类整理!A14 -> 2025-12 | B16: =IF($A16="","",SUMIF(月度成本明细!$A:$A,$A16,月度成本明细!$D:$D)) -> 1545.64 | C16: =IF($A16="","",SUMIF(月度成本明细!$A:$A,$A16,月度成本明细!$E:$E)) -> 1544.04 | D16: =IF($A16="","",B16-C16) -> 1.6 | E16: =IF($A16="","",B16/C16) -> 1.0010362 | F16: =IF($A16="","",G16/H16) -> 0.4047619 | G16: =IF($A16="","",COUNTIFS(月度成本明细!$A:$A,$A16,月度成本明细!$F:$F,"是")) -> 17 | H16: =IF($A16="","",COUNTIF(月度成本明细!$A:$A,$A16)) -> 42
A17: 合计/平均 | B17: =SUM(B5:B16) -> 18607.08 | C17: =SUM(C5:C16) -> 18528.48 | D17: =SUM(D5:D16) -> 78.6 | E17: =AVERAGE(E5:E16) -> 1.0042421 | F17: =AVERAGE(F5:F16) -> 0.49603175 | G17: =SUM(G5:G16) -> 250 | H17: =SUM(H5:H16) -> 504
A20: 二、部门预算执行对比（数据来源：部门成本汇总，超支笔次交叉核对月度成本明细）
A21: 部门 | B21: 年度总成本(万元) | C21: 年度预算(万元) | D21: 差异(万元)
A22: =分类整理!E3 -> 研发部 | B22: =IF($A22="","",SUMIF(月度成本明细!$B:$B,$A22,月度成本明细!$D:$D)) -> 2923.57 | C22: =IF($A22="","",SUMIF(月度成本明细!$B:$B,$A22,月度成本明细!$E:$E)) -> 2863.32 | D22: =B22-C22 -> 60.25
A23: =分类整理!E4 -> 市场部 | B23: =IF($A23="","",SUMIF(月度成本明细!$B:$B,$A23,月度成本明细!$D:$D)) -> 3220.53 | C23: =IF($A23="","",SUMIF(月度成本明细!$B:$B,$A23,月度成本明细!$E:$E)) -> 3285.24 | D23: =B23-C23 -> -64.71
A24: =分类整理!E5 -> 销售部 | B24: =IF($A24="","",SUMIF(月度成本明细!$B:$B,$A24,月度成本明细!$D:$D)) -> 4130.45 | C24: =IF($A24="","",SUMIF(月度成本明细!$B:$B,$A24,月度成本明细!$E:$E)) -> 4138.32 | D24: =B24-C24 -> -7.87
A25: =分类整理!E6 -> 运营部 | B25: =IF($A25="","",SUMIF(月度成本明细!$B:$B,$A25,月度成本明细!$D:$D)) -> 3005.73 | C25: =IF($A25="","",SUMIF(月度成本明细!$B:$B,$A25,月度成本明细!$E:$E)) -> 2939.76 | D25: =B25-C25 -> 65.97
A26: =分类整理!E7 -> 人力资源部 | B26: =IF($A26="","",SUMIF(月度成本明细!$B:$B,$A26,月度成本明细!$D:$D)) -> 2789.95 | C26: =IF($A26="","",SUMIF(月度成本明细!$B:$B,$A26,月度成本明细!$E:$E)) -> 2796.24 | D26: =B26-C26 -> -6.29
A27: =分类整理!E8 -> 行政部 | B27: =IF($A27="","",SUMIF(月度成本明细!$B:$B,$A27,月度成本明细!$D:$D)) -> 2536.85 | C27: =IF($A27="","",SUMIF(月度成本明细!$B:$B,$A27,月度成本明细!$E:$E)) -> 2505.6 | D27: =B27-C27 -> 31.25
A28: 合计/平均 | B28: =SUM(B22:B27) -> 18607.08 | C28: =SUM(C22:C27) -> 18528.48 | D28: =SUM(D22:D27) -> 78.6
A31: 三、采购类别成本对比（数据来源：供应商采购成本，经「数据整理」去重分组）
A32: 成本类别 | B32: 供应商采购总额(万元) | C32: 明细记录总额(万元) | D32: 供应商采购占比 | E32: 待付款笔数占比 | F32: 待付款笔数 | G32: 总笔数
A33: =分类整理!C3 -> 设备采购 | B33: =IF($A33="","",SUMIF(供应商采购成本!$B:$B,$A33,供应商采购成本!$D:$D)) -> 318.76 | C33: =IF($A33="","",SUMIF(月度成本明细!$C:$C,$A33,月度成本明细!$D:$D)) -> 3042.25 | D33: =IF($A33="","",B33/C33) -> 0.10477771 | E33: =IF($A33="","",F33/G33) -> 0.42105263 | F33: =IF($A33="","",COUNTIFS(供应商采购成本!$B:$B,$A33,供应商采购成本!$E:$E,"待付款")) -> 8 | G33: =IF($A33="","",COUNTIF(供应商采购成本!$B:$B,$A33)) -> 19
A34: =分类整理!C4 -> 云服务器费用 | B34: =IF($A34="","",SUMIF(供应商采购成本!$B:$B,$A34,供应商采购成本!$D:$D)) -> 307.6 | C34: =IF($A34="","",SUMIF(月度成本明细!$C:$C,$A34,月度成本明细!$D:$D)) -> 2769.59 | D34: =IF($A34="","",B34/C34) -> 0.11106337 | E34: =IF($A34="","",F34/G34) -> 0.27272727 | F34: =IF($A34="","",COUNTIFS(供应商采购成本!$B:$B,$A34,供应商采购成本!$E:$E,"待付款")) -> 6 | G34: =IF($A34="","",COUNTIF(供应商采购成本!$B:$B,$A34)) -> 22
A35: =分类整理!C5 -> 办公租金 | B35: =IF($A35="","",SUMIF(供应商采购成本!$B:$B,$A35,供应商采购成本!$D:$D)) -> 376.21 | C35: =IF($A35="","",SUMIF(月度成本明细!$C:$C,$A35,月度成本明细!$D:$D)) -> 2473.49 | D35: =IF($A35="","",B35/C35) -> 0.15209683 | E35: =IF($A35="","",F35/G35) -> 0.31818182 | F35: =IF($A35="","",COUNTIFS(供应商采购成本!$B:$B,$A35,供应商采购成本!$E:$E,"待付款")) -> 7 | G35: =IF($A35="","",COUNTIF(供应商采购成本!$B:$B,$A35)) -> 22
A36: =分类整理!C6 -> 市场推广费 | B36: =IF($A36="","",SUMIF(供应商采购成本!$B:$B,$A36,供应商采购成本!$D:$D)) -> 299.92 | C36: =IF($A36="","",SUMIF(月度成本明细!$C:$C,$A36,月度成本明细!$D:$D)) -> 2619.4 | D36: =IF($A36="","",B36/C36) -> 0.1144995 | E36: =IF($A36="","",F36/G36) -> 0.27272727 | F36: =IF($A36="","",COUNTIFS(供应商采购成本!$B:$B,$A36,供应商采购成本!$E:$E,"待付款")) -> 6 | G36: =IF($A36="","",COUNTIF(供应商采购成本!$B:$B,$A36)) -> 22
A37: =分类整理!C7 -> 培训费用 | B37: =IF($A37="","",SUMIF(供应商采购成本!$B:$B,$A37,供应商采购成本!$D:$D)) -> 283.46 | C37: =IF($A37="","",SUMIF(月度成本明细!$C:$C,$A37,月度成本明细!$D:$D)) -> 2516.69 | D37: =IF($A37="","",B37/C37) -> 0.11263207 | E37: =IF($A37="","",F37/G37) -> 0.38095238 | F37: =IF($A37="","",COUNTIFS(供应商采购成本!$B:$B,$A37,供应商采购成本!$E:$E,"待付款")) -> 8 | G37: =IF($A37="","",COUNTIF(供应商采购成本!$B:$B,$A37)) -> 21
A38: =分类整理!C8 -> 差旅费 | B38: =IF($A38="","",SUMIF(供应商采购成本!$B:$B,$A38,供应商采购成本!$D:$D)) -> 398.37 | C38: =IF($A38="","",SUMIF(月度成本明细!$C:$C,$A38,月度成本明细!$D:$D)) -> 2649.37 | D38: =IF($A38="","",B38/C38) -> 0.15036405 | E38: =IF($A38="","",F38/G38) -> 0.23076923 | F38: =IF($A38="","",COUNTIFS(供应商采购成本!$B:$B,$A38,供应商采购成本!$E:$E,"待付款")) -> 6 | G38: =IF($A38="","",COUNTIF(供应商采购成本!$B:$B,$A38)) -> 26
A39: 合计/平均 | B39: =SUM(B33:B38) -> 1984.32 | C39: =SUM(C33:C38) -> 16070.79 | D39: =B39/C39 -> 0.12347371 | E39: =AVERAGE(E33:E38) -> 0.31606843 | F39: =SUM(F33:F38) -> 41 | G39: =SUM(G33:G38) -> 132

Sheet 成本图表
